<?xml version="1.0" encoding="utf-8" ?>
<dwsync>
<file name="DIPL 01_o_0.jpg" server="c0300233.ferozo.com/public_html/" local="130776681790000000" remote="131443480200000000" Dst="0" />
<file name="DIPL 01_o_1.jpg" server="c0300233.ferozo.com/public_html/" local="130776681670000000" remote="131443480200000000" Dst="0" />
<file name="DIPL 01_o_2.jpg" server="c0300233.ferozo.com/public_html/" local="130776681570000000" remote="131443480200000000" Dst="0" />
<file name="DIPL 01_o_3.jpg" server="c0300233.ferozo.com/public_html/" local="130776681330000000" remote="131443480200000000" Dst="0" />
<file name="DIPL 01_o_4.jpg" server="c0300233.ferozo.com/public_html/" local="130776681150000000" remote="131443480200000000" Dst="0" />
<file name="DIPL 01_o_5.jpg" server="c0300233.ferozo.com/public_html/" local="130776681060000000" remote="131443480800000000" Dst="0" />
<file name="DIPL 01_o_800_0.jpg" server="c0300233.ferozo.com/public_html/" local="130776680710000000" remote="131443480800000000" Dst="0" />
<file name="DIPL 01_o_800_1.jpg" server="c0300233.ferozo.com/public_html/" local="130776680610000000" remote="131443480800000000" Dst="0" />
<file name="DIPL 01_o_800_2.jpg" server="c0300233.ferozo.com/public_html/" local="130776680510000000" remote="131443480800000000" Dst="0" />
<file name="DIPL 01_o_800_3.jpg" server="c0300233.ferozo.com/public_html/" local="130776680420000000" remote="131443480800000000" Dst="0" />
<file name="DIPL 01_o_800_4.jpg" server="c0300233.ferozo.com/public_html/" local="130776680340000000" remote="131443480800000000" Dst="0" />
<file name="DIPL 01_o_800_5.jpg" server="c0300233.ferozo.com/public_html/" local="130776680310000000" remote="131443480800000000" Dst="0" />
</dwsync>